dataMnp/CategoricalEncoder.py
dataMnp/DataTypeConverter.py
dataMnp/DateTimeHandler.py
dataMnp/FeatureEngineer.py
dataMnp/MissingValueHandler.py
dataMnp/OutlierHandler.py
dataMnp/TextCleaner.py
dataMnp/__init__.py
dataMnp/scaler.py
dataMnp-0.1.0.dist-info/LICENSE.txt
dataMnp-0.1.0.dist-info/METADATA
dataMnp-0.1.0.dist-info/WHEEL
dataMnp-0.1.0.dist-info/top_level.txt
dataMnp-0.1.0.dist-info/RECORD
